pylibmodbus/__init__.py
pylibmodbus/modbus_core.py
pylibmodbus/modbus_rtu.py
pylibmodbus/modbus_tcp.py
pylibmodbus-0.6.2.dist-info/LICENSE
pylibmodbus-0.6.2.dist-info/METADATA
pylibmodbus-0.6.2.dist-info/WHEEL
pylibmodbus-0.6.2.dist-info/top_level.txt
pylibmodbus-0.6.2.dist-info/RECORD
