Metadata-Version: 2.1
Name: pylibmodbus
Version: 0.6.2
Summary: Python wrapper for libmodbus
Home-page: http://github.com/stephane/pylibmodbus
Author: Stéphane Raimbault
Author-email: stephane.raimbault@gmail.com
Project-URL: Bug Tracker, https://github.com/stephane/pylibmodbus/issues
Classifier: Programming Language :: Python :: 3
Classifier: License :: OSI Approved :: BSD License
Classifier: Operating System :: OS Independent
Classifier: Intended Audience :: Developers
Classifier: Natural Language :: English
Requires-Python: >=3.7
License-File: LICENSE
Requires-Dist: cffi (>=1.15.1)
